yaml_pipe/__init__.py
yaml_pipe/cli.py
yaml_pipe-1.2.2.dist-info/entry_points.txt
yaml_pipe-1.2.2.dist-info/LICENSE
yaml_pipe-1.2.2.dist-info/WHEEL
yaml_pipe-1.2.2.dist-info/METADATA
yaml_pipe-1.2.2.dist-info/RECORD
