Metadata-Version: 2.1
Name: yaml-pipe
Version: 1.2.2
Summary: Parse yaml
Home-page: https://github.com/pollenjp/yaml-pipe
License: MIT
Author: pollenjp
Author-email: polleninjp@gmail.com
Requires-Python: >=3.8,<4.0
Classifier: License :: OSI Approved :: MIT License
Classifier: Programming Language :: Python :: 3
Classifier: Programming Language :: Python :: 3.10
Classifier: Programming Language :: Python :: 3.8
Classifier: Programming Language :: Python :: 3.9
Requires-Dist: PyYAML (>=6.0,<7.0)
Requires-Dist: omegaconf (>=2.2.2,<3.0.0)
Project-URL: Repository, https://github.com/pollenjp/yaml-pipe
